Metadata-Version: 2.1
Name: flightclient
Version: 0.6
Summary: Aircraft Tracking Library (unofficial Flightradar24 client)
Home-page: https://github.com/danilalugovoy/flightclient
Author: Danila Lugovoy
Author-email: zhestkiyflex@gmail.com
License: MIT
Platform: UNKNOWN
